charmlibs/nginx_k8s/__init__.py
charmlibs/nginx_k8s/_config.py
charmlibs/nginx_k8s/_directives.py
charmlibs/nginx_k8s/_nginx.py
charmlibs/nginx_k8s/_nginx_prometheus_exporter.py
charmlibs/nginx_k8s/_tls_config.py
charmlibs/nginx_k8s/_tracer.py
charmlibs/nginx_k8s/py.typed
charmlibs_nginx_k8s-0.1.0.dist-info/METADATA
charmlibs_nginx_k8s-0.1.0.dist-info/WHEEL
charmlibs_nginx_k8s-0.1.0.dist-info/RECORD
