Metadata-Version: 2.4
Name: charmlibs-nginx-k8s
Version: 0.1.0
Summary: Nginx sidecar container abstractions for k8s charms.
Project-URL: Documentation, https://documentation.ubuntu.com/charmlibs/reference/charmlibs/nginx_k8s/
Project-URL: Repository, https://github.com/canonical/charmlibs
Project-URL: Issues, https://github.com/canonical/charmlibs/issues
Project-URL: Changelog, https://github.com/canonical/charmlibs/blob/main/nginx_k8s/CHANGELOG.md
Author: The Observability team at Canonical Ltd.
Classifier: Development Status :: 3 - Alpha
Classifier: Intended Audience :: Developers
Classifier: License :: OSI Approved :: Apache Software License
Classifier: Operating System :: POSIX :: Linux
Classifier: Programming Language :: Python :: 3
Requires-Python: >=3.10
Requires-Dist: crossplane
Requires-Dist: ops<4,>=3
